handlers/__init__.py
handlers/es_handler/__init__.py
handlers/es_handler/models.py
handlers/rocket_handler/__init__.py
handlers/rocket_handler/models.py
handlers/rocket_handler/rocketbot/__init__.py
handlers/rotating_file_handler/__init__.py
handlers/rotating_file_handler/models.py
handlers/stream_handler/__init__.py
handlers/stream_handler/models.py
handlers_lauto-1.0.4.dist-info/LICENSE
handlers_lauto-1.0.4.dist-info/METADATA
handlers_lauto-1.0.4.dist-info/WHEEL
handlers_lauto-1.0.4.dist-info/top_level.txt
handlers_lauto-1.0.4.dist-info/RECORD
