Metadata-Version: 2.1
Name: handlers-lauto
Version: 1.0.4
Summary: Pacote para gerenciamento de logs
Home-page: https://bitbucket.org/nexfrete/handlers/src/master/
Author: L'auto Cargo Transportes Rodoviário S/A
Author-email: suporte.lautotech@gmail.com
License: MIT License
Platform: UNKNOWN
Classifier: Programming Language :: Python :: 3
Classifier: License :: OSI Approved :: MIT License
Classifier: Operating System :: OS Independent
Requires-Python: >=3.6
Requires-Dist: SQLAlchemy
Requires-Dist: attrs
Requires-Dist: certifi
Requires-Dist: chardet
Requires-Dist: elasticsearch
Requires-Dist: idna
Requires-Dist: more-itertools
Requires-Dist: packaging
Requires-Dist: pluggy
Requires-Dist: py
Requires-Dist: pyparsing
Requires-Dist: pytest
Requires-Dist: pytz
Requires-Dist: requests
Requires-Dist: requests-aws4auth
Requires-Dist: six
Requires-Dist: urllib3
Requires-Dist: wcwidth
